moshmosh/__init__.py
moshmosh/ast_compat.py
moshmosh/pattern_matching.py
moshmosh/syntax_rule.py
moshmosh_syntax-0.1.1.dist-info/LICENSE
moshmosh_syntax-0.1.1.dist-info/METADATA
moshmosh_syntax-0.1.1.dist-info/WHEEL
moshmosh_syntax-0.1.1.dist-info/entry_points.txt
moshmosh_syntax-0.1.1.dist-info/top_level.txt
moshmosh_syntax-0.1.1.dist-info/RECORD
