Metadata-Version: 2.1
Name: moshmosh-syntax
Version: 0.1.1
Summary: A hygienic syntax extension system for Python
Home-page: https://github.com/thautwarm/moshmosh
Author: thautwarm
Author-email: twshere@outlook.com
License: mit
Keywords: syntax extension,macro,pattern matching
Platform: any
Classifier: Programming Language :: Python :: 3.4
Classifier: Programming Language :: Python :: 3.5
Classifier: Programming Language :: Python :: 3.6
Classifier: Programming Language :: Python :: 3.7
Classifier: Programming Language :: Python :: Implementation :: CPython
Requires-Python: >=3
Requires-Dist: uncompyle6
